trezorlib/__init__.py
trezorlib/_ed25519.py
trezorlib/binance.py
trezorlib/btc.py
trezorlib/cardano.py
trezorlib/client.py
trezorlib/cosi.py
trezorlib/debuglink.py
trezorlib/definitions.py
trezorlib/device.py
trezorlib/eos.py
trezorlib/ethereum.py
trezorlib/exceptions.py
trezorlib/fido.py
trezorlib/log.py
trezorlib/mapping.py
trezorlib/merkle_tree.py
trezorlib/messages.py
trezorlib/misc.py
trezorlib/models.py
trezorlib/monero.py
trezorlib/nem.py
trezorlib/protobuf.py
trezorlib/py.typed
trezorlib/ripple.py
trezorlib/stellar.py
trezorlib/tezos.py
trezorlib/toif.py
trezorlib/tools.py
trezorlib/ui.py
trezorlib/_internal/__init__.py
trezorlib/_internal/emulator.py
trezorlib/_internal/firmware_headers.py
trezorlib/cli/__init__.py
trezorlib/cli/binance.py
trezorlib/cli/btc.py
trezorlib/cli/cardano.py
trezorlib/cli/cosi.py
trezorlib/cli/crypto.py
trezorlib/cli/debug.py
trezorlib/cli/device.py
trezorlib/cli/eos.py
trezorlib/cli/ethereum.py
trezorlib/cli/fido.py
trezorlib/cli/firmware.py
trezorlib/cli/monero.py
trezorlib/cli/nem.py
trezorlib/cli/ripple.py
trezorlib/cli/settings.py
trezorlib/cli/stellar.py
trezorlib/cli/tezos.py
trezorlib/cli/trezorctl.py
trezorlib/firmware/__init__.py
trezorlib/firmware/consts.py
trezorlib/firmware/core.py
trezorlib/firmware/legacy.py
trezorlib/firmware/models.py
trezorlib/firmware/util.py
trezorlib/firmware/vendor.py
trezorlib/qt/__init__.py
trezorlib/qt/pinmatrix.py
trezorlib/transport/__init__.py
trezorlib/transport/bridge.py
trezorlib/transport/hid.py
trezorlib/transport/protocol.py
trezorlib/transport/udp.py
trezorlib/transport/webusb.py
eulith_trezor-0.0.2.dist-info/AUTHORS
eulith_trezor-0.0.2.dist-info/COPYING
eulith_trezor-0.0.2.dist-info/METADATA
eulith_trezor-0.0.2.dist-info/WHEEL
eulith_trezor-0.0.2.dist-info/entry_points.txt
eulith_trezor-0.0.2.dist-info/top_level.txt
eulith_trezor-0.0.2.dist-info/RECORD
