Metadata-Version: 2.1
Name: eulith-trezor
Version: 0.0.2
Summary: Python library for communicating with Trezor Hardware Wallet (with modifications from Eulith)
Home-page: https://github.com/kristian1108/trezor-firmware
Author: Trezor & Eulith
Author-email: admin@eulith.com
License: LGPLv3
Classifier: License :: OSI Approved :: GNU Lesser General Public License v3 (LGPLv3)
Classifier: Operating System :: POSIX :: Linux
Classifier: Operating System :: Microsoft :: Windows
Classifier: Operating System :: MacOS :: MacOS X
Classifier: Programming Language :: Python :: 3 :: Only
Requires-Python: >=3.6
License-File: COPYING
License-File: AUTHORS
Requires-Dist: ecdsa (>=0.9)
Requires-Dist: mnemonic (>=0.20)
Requires-Dist: requests (>=2.4.0)
Requires-Dist: click (<8.2,>=7)
Requires-Dist: libusb1 (>=1.6.4)
Requires-Dist: construct (!=2.10.55,>=2.9)
Requires-Dist: typing-extensions (>=3.10)
Requires-Dist: construct-classes (>=0.1.2)
Requires-Dist: dataclasses ; python_version < "3.7"
Requires-Dist: rlp (==3.0.0) ; python_version >= "3.7"
Provides-Extra: ethereum
Requires-Dist: web3 (>=4.8) ; extra == 'ethereum'
Requires-Dist: rlp (>=1.1.0) ; (python_version < "3.7") and extra == 'ethereum'
Provides-Extra: extra
Requires-Dist: Pillow ; extra == 'extra'
Provides-Extra: full
Requires-Dist: hidapi (>=0.7.99.post20) ; extra == 'full'
Requires-Dist: web3 (>=4.8) ; extra == 'full'
Requires-Dist: PyQt5 ; extra == 'full'
Requires-Dist: Pillow ; extra == 'full'
Requires-Dist: stellar-sdk (<6.0.0,>=4.0.0) ; extra == 'full'
Requires-Dist: rlp (>=1.1.0) ; (python_version < "3.7") and extra == 'full'
Provides-Extra: hidapi
Requires-Dist: hidapi (>=0.7.99.post20) ; extra == 'hidapi'
Provides-Extra: qt-widgets
Requires-Dist: PyQt5 ; extra == 'qt-widgets'
Provides-Extra: stellar
Requires-Dist: stellar-sdk (<6.0.0,>=4.0.0) ; extra == 'stellar'
